report/__init__.py
report/__main__.py
report/config.toml
report/worker.py
ale_project_x-1.2.1.dist-info/METADATA
ale_project_x-1.2.1.dist-info/WHEEL
ale_project_x-1.2.1.dist-info/entry_points.txt
ale_project_x-1.2.1.dist-info/top_level.txt
ale_project_x-1.2.1.dist-info/RECORD
